jonky/__init__.py
jonky/drawable.py
jonky/helpers.py
jonky/jonky_main.py
jonky/widget_helpers.py
jonky/widgets.py
jonky-0.0.2.dist-info/METADATA
jonky-0.0.2.dist-info/WHEEL
jonky-0.0.2.dist-info/top_level.txt
jonky-0.0.2.dist-info/RECORD
